README.rst
setup.cfg
setup.py
src/ez_setup.py
src/Selenium2Library/__init__.py
src/Selenium2Library/version.py
src/Selenium2Library/webdrivermonkeypatches.py
src/Selenium2Library/keywords/__init__.py
src/Selenium2Library/keywords/_browsermanagement.py
src/Selenium2Library/keywords/_cookie.py
src/Selenium2Library/keywords/_element.py
src/Selenium2Library/keywords/_formelement.py
src/Selenium2Library/keywords/_javascript.py
src/Selenium2Library/keywords/_logging.py
src/Selenium2Library/keywords/_runonfailure.py
src/Selenium2Library/keywords/_screenshot.py
src/Selenium2Library/keywords/_selectelement.py
src/Selenium2Library/keywords/_tableelement.py
src/Selenium2Library/keywords/_waiting.py
src/Selenium2Library/keywords/_webkeywords.py
src/Selenium2Library/keywords/keywordgroup.py
src/Selenium2Library/locators/__init__.py
src/Selenium2Library/locators/customlocator.py
src/Selenium2Library/locators/elementfinder.py
src/Selenium2Library/locators/tableelementfinder.py
src/Selenium2Library/locators/windowmanager.py
src/Selenium2Library/utils/__init__.py
src/Selenium2Library/utils/browsercache.py
src/Selenium2Library/utils/librarylistener.py
src/Selenium2Library/utils/events/__init__.py
src/Selenium2Library/utils/events/event.py
src/Selenium2Library/utils/events/scope_event.py
src/weblibrary.egg-info/PKG-INFO
src/weblibrary.egg-info/SOURCES.txt
src/weblibrary.egg-info/dependency_links.txt
src/weblibrary.egg-info/requires.txt
src/weblibrary.egg-info/top_level.txt