Metadata-Version: 1.1
Name: weblibrary
Version: 1.7.4.5
Summary: Web testing library for Robot Framework
Home-page:  
Author: Dong Hao
Author-email: <longmazhanfeng@gmail.com>
License: Apache License 2.0
Keywords: robotframework testing testautomation selenium selenium2 webdriver web
Platform: any
Classifier: Development Status :: 5 - Production/Stable
Classifier: License :: OSI Approved :: Apache Software License
Classifier: Operating System :: OS Independent
Classifier: Programming Language :: Python
Classifier: Topic :: Software Development :: Testing
